dash_breakpoints_new/WindowBreakpoints.py
dash_breakpoints_new/__init__.py
dash_breakpoints_new/_imports_.py
dash_breakpoints_new-0.1.5.dist-info/licenses/LICENSE
dash_breakpoints_new-0.1.5.dist-info/METADATA
dash_breakpoints_new-0.1.5.dist-info/WHEEL
dash_breakpoints_new-0.1.5.dist-info/top_level.txt
dash_breakpoints_new-0.1.5.dist-info/RECORD
